pecebl/__init__.py
pecebl/utils.py
pecebl/version.py
pecebl/designer/__init__.py
pecebl/designer/designer.py
pecebl/ebl_kernels/__init__.py
pecebl/ebl_kernels/kernels.py
pecebl/fft_ops/__init__.py
pecebl/fft_ops/fft_ops.py
pecebl/psf_import/__init__.py
pecebl/psf_import/casino.py
pecebl/sem/__init__.py
pecebl/sem/supra40.py
scripts/__init__.py
scripts/cli_demo.py
pecebl-0.0.1.dist-info/LICENSE.txt
pecebl-0.0.1.dist-info/METADATA
pecebl-0.0.1.dist-info/WHEEL
pecebl-0.0.1.dist-info/entry_points.txt
pecebl-0.0.1.dist-info/top_level.txt
pecebl-0.0.1.dist-info/RECORD
