Metadata-Version: 2.1
Name: pecebl
Version: 0.0.1
Summary: eBeam Lithography simulation and Proximity Effect Correction
Home-page: http://github.com/looninho/pecebl
Author: Luan Nguyen
Author-email: looninho@gmail.com
License: GPLv3
Keywords: lithography,proximity effect correction,ebl,pec,fft,convolution,deconvolution,ebeam-lithography,monte-carlo-simulation,casino,casino3
Platform: UNKNOWN
Classifier: Development Status :: 3 - Alpha
Classifier: Intended Audience :: Science/Research
Classifier: Intended Audience :: Developers
Classifier: License :: OSI Approved :: GNU General Public License v3 (GPLv3)
Classifier: Natural Language :: English
Classifier: Operating System :: Microsoft :: Windows :: Windows 10
Classifier: Operating System :: POSIX :: Linux
Classifier: Topic :: Software Development
Classifier: Topic :: Scientific/Engineering
Classifier: Topic :: Scientific/Engineering :: Visualization
Classifier: Programming Language :: Python :: 3.7
Requires-Python: >=3.7
Requires-Dist: ipython (==7.8.0)
Requires-Dist: jupyter
Requires-Dist: numba
Requires-Dist: numpy
Requires-Dist: scipy
Requires-Dist: sympy
Requires-Dist: pandas
Requires-Dist: pyqtgraph
Requires-Dist: pyopengl
Requires-Dist: matplotlib
Requires-Dist: imageio
Requires-Dist: pyculib
Requires-Dist: pycuda
Requires-Dist: scikit-cuda
